mensajes/__init__.py
mensajes/adios/__init__.py
mensajes/adios/despedidas.py
mensajes/hola/__init__.py
mensajes/hola/saludos.py
tests/__init__.py
tests/test_hola.py
Mensajes_hanselt_abel-5.3.dist-info/LICENSE
Mensajes_hanselt_abel-5.3.dist-info/METADATA
Mensajes_hanselt_abel-5.3.dist-info/WHEEL
Mensajes_hanselt_abel-5.3.dist-info/top_level.txt
Mensajes_hanselt_abel-5.3.dist-info/RECORD
